{
  "name": "Moonbeam testnet",
  "alias": "moonbeam-testnet",
  "id": "1287",
  "symbol": "testGLMR",
  "testnet": true,
  "providers": [
    {
      "alias": "default",
      "rpcUrl": "https://rpc.api.moonbase.moonbeam.network"
    }
  ],
  "explorer": {
    "api": {
      "url": "https://api-moonbase.moonscan.io/api",
      "key": {
        "required": true,
        "hardhatEtherscanAlias": "moonbaseAlpha"
      }
    },
    "browserUrl": "https://moonbase.moonscan.io/"
  },
  "blockTimeMs": 13654
}
